openmldb_exporter/.DS_Store
openmldb_exporter/__init__.py
openmldb_exporter/collector/__init__.py
openmldb_exporter/collector/collectors.py
openmldb_exporter/collector/configstore.py
openmldb_exporter/collector/metrics.py
openmldb_exporter/exporter.py
openmldb_exporter-0.9.0.dist-info/LICENSE
openmldb_exporter-0.9.0.dist-info/METADATA
openmldb_exporter-0.9.0.dist-info/WHEEL
openmldb_exporter-0.9.0.dist-info/entry_points.txt
openmldb_exporter-0.9.0.dist-info/RECORD
