Metadata-Version: 2.1
Name: openmldb-exporter
Version: 0.9.0
Summary: prometheus exporter for OpenMLDB
Home-page: https://openmldb.ai
License: Apache-2.0
Keywords: openmldb,prometheus
Author: aceforeverd
Author-email: teapot@aceforeverd.com
Requires-Python: >=3.8,<4.0
Classifier: License :: OSI Approved :: Apache Software License
Classifier: Programming Language :: Python :: 3
Classifier: Programming Language :: Python :: 3.8
Classifier: Programming Language :: Python :: 3.9
Classifier: Programming Language :: Python :: 3.10
Classifier: Programming Language :: Python :: 3.11
Classifier: Programming Language :: Python :: 3.12
Classifier: Topic :: Database
Classifier: Topic :: System :: Monitoring
Requires-Dist: Twisted (>=22.2,<24.0)
Requires-Dist: openmldb (>=0.8.4,<0.9.0)
Requires-Dist: prometheus-client (>=0.19.0,<0.20.0)
Project-URL: Documentation, https://openmldb.ai/docs/zh/main/maintain/monitoring.html
Project-URL: Repository, https://github.com/4paradigm/openmldb-exporter
